annotator/__init__.py
annotator/cli.py
annotator/core.py
annotator/defaults.py
annotator_cli-0.1.0.dist-info/licenses/LICENSE
annotator_cli-0.1.0.dist-info/METADATA
annotator_cli-0.1.0.dist-info/WHEEL
annotator_cli-0.1.0.dist-info/entry_points.txt
annotator_cli-0.1.0.dist-info/top_level.txt
annotator_cli-0.1.0.dist-info/RECORD
