Metadata-Version: 2.4
Name: annotator-cli
Version: 0.1.0
Summary: Annotates source files with their relative paths for easier AI/debug context
Requires-Python: >=3.12
License-File: LICENSE
Dynamic: license-file
